ls_ml_toolkit/__init__.py
ls_ml_toolkit/config_loader.py
ls_ml_toolkit/env_loader.py
ls_ml_toolkit/optimize_onnx.py
ls_ml_toolkit/train.py
ls_ml_toolkit/ui.py
ls_ml_toolkit-1.0.2.dist-info/licenses/LICENSE
ls_ml_toolkit-1.0.2.dist-info/METADATA
ls_ml_toolkit-1.0.2.dist-info/WHEEL
ls_ml_toolkit-1.0.2.dist-info/entry_points.txt
ls_ml_toolkit-1.0.2.dist-info/top_level.txt
ls_ml_toolkit-1.0.2.dist-info/RECORD
