Metadata-Version: 2.4
Name: ls-ml-toolkit
Version: 1.0.2
Summary: Label Studio ML Toolkit: Convert, Train, Optimize object detection models (CPU only)
Home-page: https://github.com/bavix/ls-ml-toolkit
Author: Babichev Maxim
Author-email: Babichev Maxim <info@babichev.net>
Maintainer-email: Babichev Maxim <info@babichev.net>
License: MIT
Project-URL: Homepage, https://github.com/bavix/ls-ml-toolkit
Project-URL: Repository, https://github.com/bavix/ls-ml-toolkit
Project-URL: Issues, https://github.com/bavix/ls-ml-toolkit/issues
Project-URL: Documentation, https://github.com/bavix/ls-ml-toolkit#readme
Keywords: label-studio,yolo,object-detection,machine-learning,computer-vision,ml-toolkit,dataset-conversion,model-training,onnx-optimization
Classifier: Development Status :: 4 - Beta
Classifier: Intended Audience :: Developers
Classifier: Intended Audience :: Science/Research
Classifier: License :: OSI Approved :: MIT License
Classifier: Operating System :: OS Independent
Classifier: Programming Language :: Python :: 3
Classifier: Programming Language :: Python :: 3.8
Classifier: Programming Language :: Python :: 3.9
Classifier: Programming Language :: Python :: 3.10
Classifier: Programming Language :: Python :: 3.11
Classifier: Programming Language :: Python :: 3.12
Classifier: Topic :: Scientific/Engineering :: Artificial Intelligence
Classifier: Topic :: Software Development :: Libraries :: Python Modules
Requires-Python: >=3.8
License-File: LICENSE
Requires-Dist: ultralytics>=8.0.0
Requires-Dist: onnx>=1.15.0
Requires-Dist: onnxruntime>=1.16.0
Requires-Dist: tqdm>=4.65.0
Requires-Dist: requests>=2.31.0
Requires-Dist: PyYAML>=6.0.0
Requires-Dist: boto3>=1.34.0
Requires-Dist: botocore>=1.34.0
Requires-Dist: torch>=2.0.0
Requires-Dist: torchvision>=0.15.0
Dynamic: author
Dynamic: home-page
Dynamic: license-file
Dynamic: requires-python
